.VERSION
AUTHORS.rst
CONTRIBUTING.rst
HISTORY.rst
LICENSE
MANIFEST.in
Pipfile
Pipfile.lock
README.rst
USAGE.rst
dev-requirements.txt
requirements.txt
setup.cfg
setup.py
awsfindingsmanagerlib/.VERSION
awsfindingsmanagerlib/AUTHORS.rst
awsfindingsmanagerlib/CONTRIBUTING.rst
awsfindingsmanagerlib/HISTORY.rst
awsfindingsmanagerlib/LICENSE
awsfindingsmanagerlib/Pipfile
awsfindingsmanagerlib/Pipfile.lock
awsfindingsmanagerlib/README.rst
awsfindingsmanagerlib/USAGE.rst
awsfindingsmanagerlib/__init__.py
awsfindingsmanagerlib/_version.py
awsfindingsmanagerlib/awsfindingsmanagerlib.py
awsfindingsmanagerlib/awsfindingsmanagerlibexceptions.py
awsfindingsmanagerlib/backends.py
awsfindingsmanagerlib/configuration.py
awsfindingsmanagerlib/dev-requirements.txt
awsfindingsmanagerlib/requirements.txt
awsfindingsmanagerlib/validations.py
awsfindingsmanagerlib.egg-info/PKG-INFO
awsfindingsmanagerlib.egg-info/SOURCES.txt
awsfindingsmanagerlib.egg-info/dependency_links.txt
awsfindingsmanagerlib.egg-info/not-zip-safe
awsfindingsmanagerlib.egg-info/requires.txt
awsfindingsmanagerlib.egg-info/top_level.txt
docs/Makefile
docs/authors.rst
docs/conf.py
docs/contributing.rst
docs/history.rst
docs/index.rst
docs/installation.rst
docs/readme.rst
docs/usage.rst
tests/test_requests.py
tests/test_suppressions.py