Metadata-Version: 2.4
Name: awsfindingsmanagerlib
Version: 1.3.1
Summary: A library to manage findings in AWS.
Home-page: https://github.com/schubergphilis/awsfindingsmanagerlib.git
Author: Marwin Baumann
Author-email: mbaumann@schubergphilis.com
License: Apache Software License 2.0
Keywords: awsfindingsmanagerlib securityhub findings aws
Classifier: Development Status :: 4 - Beta
Classifier: Intended Audience :: Developers
Classifier: License :: OSI Approved :: Apache Software License
Classifier: Natural Language :: English
Classifier: Programming Language :: Python :: 3.8
License-File: LICENSE
License-File: AUTHORS.rst
Requires-Dist: boto3>=1.40.31; python_version >= "3.9"
Requires-Dist: opnieuw>=3.1.0; python_version >= "3.8"
Requires-Dist: python-dateutil>=2.9.0.post0; python_version >= "2.7" and python_version not in "3.0, 3.1, 3.2"
Requires-Dist: schema~=0.7.7
Requires-Dist: requests~=2.32.5; python_version >= "3.9"
Requires-Dist: pyyaml~=6.0.2; python_version >= "3.8"
Dynamic: author
Dynamic: author-email
Dynamic: classifier
Dynamic: description
Dynamic: home-page
Dynamic: keywords
Dynamic: license
Dynamic: license-file
Dynamic: requires-dist
Dynamic: summary
